chorey/__init__.py
chorey/_types.py
chorey/branch.py
chorey/cli.py
chorey/context.py
chorey/error.py
chorey/main.py
chorey/mermaid.py
chorey/mixins.py
chorey/route.py
chorey/step.py
chorey/utils.py
chorey-0.1.0.dist-info/LICENSE
chorey-0.1.0.dist-info/METADATA
chorey-0.1.0.dist-info/WHEEL
chorey-0.1.0.dist-info/entry_points.txt
chorey-0.1.0.dist-info/RECORD
