Metadata-Version: 2.3
Name: chorey
Version: 0.1.0
Summary: Asynchronous, Type-Safe Python Pipeline Framework
License: MIT
Author: anwitars
Author-email: anwitarsbusiness@gmail.com
Requires-Python: >=3.11
Classifier: Programming Language :: Python :: 3.12
Classifier: Programming Language :: Python :: 3.11
Classifier: License :: OSI Approved :: MIT License
Classifier: Operating System :: OS Independent
Classifier: Topic :: Software Development :: Libraries
Classifier: Topic :: Software Development :: Libraries :: Application Frameworks
Classifier: Topic :: Software Development :: Libraries :: Python Modules
Provides-Extra: cli
Requires-Dist: pydantic (>=2.12.0,<3.0.0)
Requires-Dist: typer (>=0.19.2,<0.20.0) ; extra == "cli"
Project-URL: Homepage, https://anwitars.github.io/chorey
